.env
cli.py
readme.md
requirements.txt
utils.py
devgossip_v2-2.4.3.dist-info/entry_points.txt
devgossip_v2-2.4.3.dist-info/WHEEL
devgossip_v2-2.4.3.dist-info/METADATA
devgossip_v2-2.4.3.dist-info/RECORD
