Metadata-Version: 2.1
Name: devgossip-v2
Version: 2.4.3
Summary: A commandline forum application.
Author: Mark Okhakumhe
Requires-Python: >=3.8,<4.0
Classifier: Programming Language :: Python :: 3
Classifier: Programming Language :: Python :: 3.8
Requires-Dist: colorama (>=0.4.3,<0.5.0)
Requires-Dist: pusher (>=3.0.0,<4.0.0)
Requires-Dist: pysher (>=1.0.6,<2.0.0)
Requires-Dist: termcolor (>=1.1.0,<2.0.0)
